bits/__init__.py
bits/people/__init__.py
bits/people/api_v1.py
bits/people/mysql.py
bits/people/people.py
bits/people/person.py
bits_people-1.0.6.dist-info/METADATA
bits_people-1.0.6.dist-info/WHEEL
bits_people-1.0.6.dist-info/top_level.txt
bits_people-1.0.6.dist-info/RECORD
