Metadata-Version: 2.1
Name: bits-people
Version: 1.0.6
Summary: BITS People
Home-page: UNKNOWN
Author: Lukas Karlsson
Author-email: karlsson@broadinstitute.org
License: Apache Software License
Platform: UNKNOWN
Requires-Dist: bits-mysql
Requires-Dist: google-auth
Requires-Dist: google-cloud-bigquery
Requires-Dist: google-cloud-firestore
